imageurlscraper/__init__.py
imageurlscraper/asiachan.py
imageurlscraper/googledrive.py
imageurlscraper/imgur.py
imageurlscraper/main.py
imageurlscraper/pool.py
services/__init__.py
services/asiachan.py
services/googledrive.py
services/imgur.py
services/pool.py
imageurlscraper-1.0.0.dist-info/METADATA
imageurlscraper-1.0.0.dist-info/WHEEL
imageurlscraper-1.0.0.dist-info/top_level.txt
imageurlscraper-1.0.0.dist-info/RECORD
