Metadata-Version: 2.1
Name: imageurlscraper
Version: 1.0.0
Summary: Image Scraper for Google Drive, Imgur, AsiaChan, and more.
Home-page: https://github.com/MujyKun/ImageURLScraper/
Author: MujyKun
Author-email: thugystory1@gmail.com
License: MIT License
Platform: UNKNOWN
Classifier: Development Status :: 5 - Production/Stable
Classifier: License :: OSI Approved :: MIT License
Classifier: Programming Language :: Python
Requires-Python: >=2.7
Requires-Dist: urllib3 (==1.25.7)
Requires-Dist: beautifulsoup4 (==4.8.2)
Requires-Dist: google-api-python-client (==1.7.11)
Requires-Dist: google-auth (==1.10.0)
Requires-Dist: google-auth-httplib2 (==0.0.3)
Requires-Dist: google-auth-oauthlib (==0.4.1)
